neuron_morphology_tools/__init__.py
neuron_morphology_tools/morphopy_utils.py
neuron_morphology_tools/neuron_nx_feature_processing.py
neuron_morphology_tools/neuron_nx_io.py
neuron_morphology_tools/neuron_nx_stats.py
neuron_morphology_tools/neuron_nx_utils.py
neuron_morphology_tools/neuron_skeleton_utils.py
neuron_morphology_tools-1.0.1.dist-info/DESCRIPTION.rst
neuron_morphology_tools-1.0.1.dist-info/METADATA
neuron_morphology_tools-1.0.1.dist-info/RECORD
neuron_morphology_tools-1.0.1.dist-info/WHEEL
neuron_morphology_tools-1.0.1.dist-info/metadata.json
neuron_morphology_tools-1.0.1.dist-info/top_level.txt
