Metadata-Version: 2.0
Name: neuron-morphology-tools
Version: 1.0.1
Summary: UNKNOWN
Home-page: UNKNOWN
Author: Brendan Celii
Author-email: brendanacelii@gmail.com
License: UNKNOWN
Project-URL: Source, https://github.com/reimerlab/neuron_morphology_tools
Project-URL: Documentation, https://reimerlab.github.io/neuron_morphology_tools/
Platform: UNKNOWN
Requires-Dist: matplotlib (>=3.3.4)
Requires-Dist: morphopy (>=0.7.2)
Requires-Dist: networkx (>=2.5)
Requires-Dist: numpy (>=1.19.5)
Requires-Dist: pandas (>=1.1.5)
Requires-Dist: pykdtree (>=1.3.1)
Requires-Dist: scipy (>=1.5.4)
Requires-Dist: seaborn (>=0.11.2)
Requires-Dist: ipython
Requires-Dist: ipython-genutils
Requires-Dist: datasci-stdlib-tools (>=1.0.1)
